Pymeshit_workflow_gui.py
main.py
Pymeshit/__init__.py
Pymeshit/intersection_utils.py
Pymeshit/tetra_mesh_utils.py
Pymeshit/triangle_direct.py
Pymeshit/core/__init__.py
pymeshit-0.6.1.dist-info/licenses/LICENSE
pymeshit-0.6.1.dist-info/METADATA
pymeshit-0.6.1.dist-info/WHEEL
pymeshit-0.6.1.dist-info/entry_points.txt
pymeshit-0.6.1.dist-info/top_level.txt
pymeshit-0.6.1.dist-info/RECORD
